rtmidi2.cpython-310-darwin.so
rtmidi2-1.4.1.dist-info/RECORD
rtmidi2-1.4.1.dist-info/WHEEL
rtmidi2-1.4.1.dist-info/top_level.txt
rtmidi2-1.4.1.dist-info/METADATA
rtmidi2-1.4.1.dist-info/licenses/LICENSE
