Metadata-Version: 2.4
Name: rtmidi2
Version: 1.4.1
Summary: Python wrapper for RtMidi written in Cython. Allows sending raw messages, multi-port input and sending multiple messages in one call.
Home-page: https://github.com/gesellkammer/rtmidi2
Author: originally by Guido Lorenz, modified by Eduardo Moguillansky
Author-email: eduardo.moguillansky@gmail.com
License: MIT
Platform: any
Classifier: Development Status :: 4 - Beta
Classifier: Programming Language :: Cython
Classifier: Topic :: Multimedia :: Sound/Audio :: MIDI
Classifier: License :: OSI Approved :: MIT License
Classifier: Programming Language :: Python :: 3
Classifier: Topic :: Software Development :: Libraries :: Python Modules
Requires-Python: >=3.8
License-File: LICENSE
Dynamic: author
Dynamic: author-email
Dynamic: classifier
Dynamic: description
Dynamic: home-page
Dynamic: license
Dynamic: license-file
Dynamic: platform
Dynamic: requires-python
Dynamic: summary
